odoo/addons/web_access_rule_buttons/README.rst
odoo/addons/web_access_rule_buttons/__init__.py
odoo/addons/web_access_rule_buttons/__manifest__.py
odoo/addons/web_access_rule_buttons/i18n/de.po
odoo/addons/web_access_rule_buttons/i18n/web_access_rule_buttons.pot
odoo/addons/web_access_rule_buttons/models/__init__.py
odoo/addons/web_access_rule_buttons/models/models.py
odoo/addons/web_access_rule_buttons/readme/CONTRIBUTORS.rst
odoo/addons/web_access_rule_buttons/readme/DESCRIPTION.rst
odoo/addons/web_access_rule_buttons/readme/USAGE.rst
odoo/addons/web_access_rule_buttons/static/description/icon.png
odoo/addons/web_access_rule_buttons/static/description/index.html
odoo/addons/web_access_rule_buttons/static/src/js/form_controller.js
odoo/addons/web_access_rule_buttons/tests/__init__.py
odoo/addons/web_access_rule_buttons/tests/test_access_rule_buttons.py
odoo/addons/web_access_rule_buttons/views/web_access_rule_buttons.xml
odoo14_addon_web_access_rule_buttons-14.0.1.0.1.dist-info/METADATA
odoo14_addon_web_access_rule_buttons-14.0.1.0.1.dist-info/WHEEL
odoo14_addon_web_access_rule_buttons-14.0.1.0.1.dist-info/top_level.txt
odoo14_addon_web_access_rule_buttons-14.0.1.0.1.dist-info/RECORD
